[
  {
    "rank": 1,
    "tier": 1,
    "name": "jamarr chase"
  },
  {
    "rank": 2,
    "tier": 1,
    "name": "bijan robinson"
  },
  {
    "rank": 3,
    "tier": 1,
    "name": "jahmyr gibbs"
  },
  {
    "rank": 4,
    "tier": 1,
    "name": "saquon barkley"
  },
  {
    "rank": 5,
    "tier": 1,
    "name": "justin jefferson"
  },
  {
    "rank": 6,
    "tier": 1,
    "name": "ceedee lamb"
  },
  {
    "rank": 7,
    "tier": 2,
    "name": "malik nabers"
  },
  {
    "rank": 8,
    "tier": 2,
    "name": "nico collins"
  },
  {
    "rank": 9,
    "tier": 2,
    "name": "amon-ra st brown"
  },
  {
    "rank": 10,
    "tier": 2,
    "name": "christian mccaffrey"
  },
  {
    "rank": 11,
    "tier": 2,
    "name": "puka nacua"
  },
  {
    "rank": 12,
    "tier": 2,
    "name": "derrick henry"
  },
  {
    "rank": 13,
    "tier": 2,
    "name": "brian thomas"
  },
  {
    "rank": 14,
    "tier": 2,
    "name": "ashton jeanty"
  },
  {
    "rank": 15,
    "tier": 2,
    "name": "devon achane"
  },
  {
    "rank": 16,
    "tier": 3,
    "name": "drake london"
  },
  {
    "rank": 17,
    "tier": 3,
    "name": "aj brown"
  },
  {
    "rank": 18,
    "tier": 3,
    "name": "brock bowers"
  },
  {
    "rank": 19,
    "tier": 3,
    "name": "jonathan taylor"
  },
  {
    "rank": 20,
    "tier": 3,
    "name": "josh jacobs"
  },
  {
    "rank": 21,
    "tier": 3,
    "name": "bucky irving"
  },
  {
    "rank": 22,
    "tier": 3,
    "name": "chase brown"
  },
  {
    "rank": 23,
    "tier": 4,
    "name": "trey mcbride"
  },
  {
    "rank": 24,
    "tier": 4,
    "name": "ladd mcconkey"
  },
  {
    "rank": 25,
    "tier": 4,
    "name": "kyren williams"
  },
  {
    "rank": 26,
    "tier": 4,
    "name": "josh allen"
  },
  {
    "rank": 27,
    "tier": 4,
    "name": "lamar jackson"
  },
  {
    "rank": 28,
    "tier": 4,
    "name": "jaxon smith-njigba"
  },
  {
    "rank": 29,
    "tier": 4,
    "name": "tee higgins"
  },
  {
    "rank": 30,
    "tier": 5,
    "name": "tyreek hill"
  },
  {
    "rank": 31,
    "tier": 5,
    "name": "george kittle"
  },
  {
    "rank": 32,
    "tier": 5,
    "name": "garrett wilson"
  },
  {
    "rank": 33,
    "tier": 5,
    "name": "mike evans"
  },
  {
    "rank": 34,
    "tier": 5,
    "name": "jayden daniels"
  },
  {
    "rank": 35,
    "tier": 5,
    "name": "davante adams"
  },
  {
    "rank": 36,
    "tier": 5,
    "name": "james cook"
  },
  {
    "rank": 37,
    "tier": 5,
    "name": "jalen hurts"
  },
  {
    "rank": 38,
    "tier": 6,
    "name": "kenneth walker"
  },
  {
    "rank": 39,
    "tier": 6,
    "name": "omarion hampton"
  },
  {
    "rank": 40,
    "tier": 6,
    "name": "breece hall"
  },
  {
    "rank": 41,
    "tier": 6,
    "name": "marvin harrison"
  },
  {
    "rank": 42,
    "tier": 6,
    "name": "alvin kamara"
  },
  {
    "rank": 43,
    "tier": 6,
    "name": "terry mclaurin"
  },
  {
    "rank": 44,
    "tier": 6,
    "name": "dj moore"
  },
  {
    "rank": 45,
    "tier": 7,
    "name": "dk metcalf"
  },
  {
    "rank": 46,
    "tier": 7,
    "name": "joe burrow"
  },
  {
    "rank": 47,
    "tier": 7,
    "name": "chuba hubbard"
  },
  {
    "rank": 48,
    "tier": 7,
    "name": "james conner"
  },
  {
    "rank": 49,
    "tier": 7,
    "name": "courtland sutton"
  },
  {
    "rank": 50,
    "tier": 8,
    "name": "devonta smith"
  },
  {
    "rank": 51,
    "tier": 8,
    "name": "jameson williams"
  },
  {
    "rank": 52,
    "tier": 8,
    "name": "treveyon henderson"
  },
  {
    "rank": 53,
    "tier": 8,
    "name": "tetairoa mcmillan"
  },
  {
    "rank": 54,
    "tier": 8,
    "name": "zay flowers"
  },
  {
    "rank": 55,
    "tier": 9,
    "name": "xavier worthy"
  },
  {
    "rank": 56,
    "tier": 9,
    "name": "george pickens"
  },
  {
    "rank": 57,
    "tier": 9,
    "name": "calvin ridley"
  },
  {
    "rank": 58,
    "tier": 9,
    "name": "david montgomery"
  },
  {
    "rank": 59,
    "tier": 9,
    "name": "dandre swift"
  },
  {
    "rank": 60,
    "tier": 9,
    "name": "jaylen waddle"
  },
  {
    "rank": 61,
    "tier": 9,
    "name": "tony pollard"
  },
  {
    "rank": 62,
    "tier": 9,
    "name": "sam laporta"
  },
  {
    "rank": 63,
    "tier": 10,
    "name": "isiah pacheco"
  },
  {
    "rank": 64,
    "tier": 10,
    "name": "rashee rice"
  },
  {
    "rank": 65,
    "tier": 10,
    "name": "rj harvey"
  },
  {
    "rank": 66,
    "tier": 10,
    "name": "aaron jones"
  },
  {
    "rank": 67,
    "tier": 10,
    "name": "patrick mahomes"
  },
  {
    "rank": 68,
    "tier": 11,
    "name": "travis hunter"
  },
  {
    "rank": 69,
    "tier": 11,
    "name": "tj hockenson"
  },
  {
    "rank": 70,
    "tier": 11,
    "name": "chris olave"
  },
  {
    "rank": 71,
    "tier": 12,
    "name": "baker mayfield"
  },
  {
    "rank": 72,
    "tier": 12,
    "name": "kaleb johnson"
  },
  {
    "rank": 73,
    "tier": 12,
    "name": "jerry jeudy"
  },
  {
    "rank": 74,
    "tier": 12,
    "name": "rome odunze"
  },
  {
    "rank": 75,
    "tier": 12,
    "name": "brian robinson"
  },
  {
    "rank": 76,
    "tier": 12,
    "name": "tyrone tracy"
  },
  {
    "rank": 77,
    "tier": 12,
    "name": "bo nix"
  },
  {
    "rank": 78,
    "tier": 12,
    "name": "mark andrews"
  },
  {
    "rank": 79,
    "tier": 12,
    "name": "travis kelce"
  },
  {
    "rank": 80,
    "tier": 13,
    "name": "kyler murray"
  },
  {
    "rank": 81,
    "tier": 13,
    "name": "joe mixon"
  },
  {
    "rank": 82,
    "tier": 13,
    "name": "jakobi meyers"
  },
  {
    "rank": 83,
    "tier": 13,
    "name": "jaylen warren"
  },
  {
    "rank": 84,
    "tier": 13,
    "name": "stefon diggs"
  },
  {
    "rank": 85,
    "tier": 13,
    "name": "ricky pearsall"
  },
  {
    "rank": 86,
    "tier": 13,
    "name": "jordan addison"
  },
  {
    "rank": 87,
    "tier": 13,
    "name": "david njoku"
  },
  {
    "rank": 88,
    "tier": 13,
    "name": "dak prescott"
  },
  {
    "rank": 89,
    "tier": 13,
    "name": "travis etienne"
  },
  {
    "rank": 90,
    "tier": 13,
    "name": "jauan jennings"
  },
  {
    "rank": 91,
    "tier": 14,
    "name": "evan engram"
  },
  {
    "rank": 92,
    "tier": 14,
    "name": "jordan mason"
  },
  {
    "rank": 93,
    "tier": 14,
    "name": "brock purdy"
  },
  {
    "rank": 94,
    "tier": 14,
    "name": "deebo samuel"
  },
  {
    "rank": 95,
    "tier": 14,
    "name": "chris godwin"
  },
  {
    "rank": 96,
    "tier": 14,
    "name": "khalil shakir"
  },
  {
    "rank": 97,
    "tier": 14,
    "name": "justin fields"
  },
  {
    "rank": 98,
    "tier": 14,
    "name": "tucker kraft"
  },
  {
    "rank": 99,
    "tier": 15,
    "name": "justin herbert"
  },
  {
    "rank": 100,
    "tier": 15,
    "name": "jayden reed"
  },
  {
    "rank": 101,
    "tier": 15,
    "name": "emeka egbuka"
  },
  {
    "rank": 102,
    "tier": 15,
    "name": "zach charbonnet"
  },
  {
    "rank": 103,
    "tier": 15,
    "name": "javonte williams"
  },
  {
    "rank": 104,
    "tier": 15,
    "name": "jk dobbins"
  },
  {
    "rank": 105,
    "tier": 15,
    "name": "rhamondre stevenson"
  },
  {
    "rank": 106,
    "tier": 15,
    "name": "jared goff"
  },
  {
    "rank": 107,
    "tier": 15,
    "name": "josh downs"
  },
  {
    "rank": 108,
    "tier": 15,
    "name": "caleb williams"
  },
  {
    "rank": 109,
    "tier": 15,
    "name": "drake maye"
  },
  {
    "rank": 110,
    "tier": 16,
    "name": "tyler warren"
  },
  {
    "rank": 111,
    "tier": 16,
    "name": "cooper kupp"
  },
  {
    "rank": 112,
    "tier": 16,
    "name": "jordan love"
  },
  {
    "rank": 113,
    "tier": 16,
    "name": "michael pittman"
  },
  {
    "rank": 114,
    "tier": 16,
    "name": "tank bigsby"
  },
  {
    "rank": 115,
    "tier": 17,
    "name": "jake ferguson"
  },
  {
    "rank": 116,
    "tier": 17,
    "name": "cam skattebo"
  },
  {
    "rank": 117,
    "tier": 17,
    "name": "trevor lawrence"
  },
  {
    "rank": 118,
    "tier": 15,
    "name": "matthew golden"
  },
  {
    "rank": 119,
    "tier": 17,
    "name": "dalton kincaid"
  },
  {
    "rank": 120,
    "tier": 17,
    "name": "darnell mooney"
  },
  {
    "rank": 121,
    "tier": 17,
    "name": "cj stroud"
  },
  {
    "rank": 122,
    "tier": 17,
    "name": "quinshon judkins"
  },
  {
    "rank": 123,
    "tier": 17,
    "name": "tyjae spears"
  },
  {
    "rank": 124,
    "tier": 17,
    "name": "najee harris"
  },
  {
    "rank": 125,
    "tier": 17,
    "name": "dallas goedert"
  },
  {
    "rank": 126,
    "tier": 17,
    "name": "rachaad white"
  },
  {
    "rank": 127,
    "tier": 18,
    "name": "keon coleman"
  },
  {
    "rank": 128,
    "tier": 18,
    "name": "jj mccarthy"
  },
  {
    "rank": 129,
    "tier": 18,
    "name": "brandon aiyuk"
  },
  {
    "rank": 130,
    "tier": 18,
    "name": "rashid shaheed"
  },
  {
    "rank": 131,
    "tier": 18,
    "name": "ray davis"
  },
  {
    "rank": 132,
    "tier": 18,
    "name": "colston loveland"
  },
  {
    "rank": 133,
    "tier": 19,
    "name": "austin ekeler"
  },
  {
    "rank": 134,
    "tier": 19,
    "name": "christian kirk"
  },
  {
    "rank": 135,
    "tier": 19,
    "name": "braelon allen"
  },
  {
    "rank": 136,
    "tier": 19,
    "name": "jaydon blue"
  },
  {
    "rank": 137,
    "tier": 19,
    "name": "trey benson"
  },
  {
    "rank": 138,
    "tier": 19,
    "name": "kyle pitts"
  },
  {
    "rank": 139,
    "tier": 19,
    "name": "tyler allgeier"
  },
  {
    "rank": 140,
    "tier": 19,
    "name": "rashod bateman"
  },
  {
    "rank": 141,
    "tier": 19,
    "name": "tua tagovailoa"
  },
  {
    "rank": 142,
    "tier": 19,
    "name": "hunter henry"
  },
  {
    "rank": 143,
    "tier": 19,
    "name": "jerome ford"
  },
  {
    "rank": 144,
    "tier": 19,
    "name": "luther burden"
  },
  {
    "rank": 145,
    "tier": 20,
    "name": "cedric tillman"
  },
  {
    "rank": 146,
    "tier": 20,
    "name": "bryce young"
  },
  {
    "rank": 147,
    "tier": 20,
    "name": "isaac guerendo"
  },
  {
    "rank": 148,
    "tier": 21,
    "name": "rico dowdle"
  },
  {
    "rank": 149,
    "tier": 21,
    "name": "michael penix"
  },
  {
    "rank": 150,
    "tier": 21,
    "name": "marvin mims"
  },
  {
    "rank": 151,
    "tier": 21,
    "name": "jonnu smith"
  },
  {
    "rank": 152,
    "tier": 21,
    "name": "nick chubb"
  },
  {
    "rank": 153,
    "tier": 22,
    "name": "romeo doubs"
  },
  {
    "rank": 154,
    "tier": 22,
    "name": "zach ertz"
  },
  {
    "rank": 155,
    "tier": 20,
    "name": "jayden higgins"
  },
  {
    "rank": 156,
    "tier": 21,
    "name": "bhayshul tuten"
  },
  {
    "rank": 157,
    "tier": 22,
    "name": "matthew stafford"
  },
  {
    "rank": 158,
    "tier": 21,
    "name": "jaylen wright"
  },
  {
    "rank": 159,
    "tier": 21,
    "name": "dylan sampson"
  },
  {
    "rank": 160,
    "tier": 22,
    "name": "marquise brown"
  },
  {
    "rank": 161,
    "tier": 23,
    "name": "kyle williams"
  },
  {
    "rank": 162,
    "tier": 22,
    "name": "keenan allen"
  },
  {
    "rank": 163,
    "tier": 23,
    "name": "geno smith"
  },
  {
    "rank": 164,
    "tier": 23,
    "name": "wandale robinson"
  },
  {
    "rank": 165,
    "tier": 23,
    "name": "tre harris"
  },
  {
    "rank": 166,
    "tier": 23,
    "name": "adam thielen"
  },
  {
    "rank": 167,
    "tier": 23,
    "name": "roschon johnson"
  },
  {
    "rank": 168,
    "tier": 23,
    "name": "jalen mcmillan"
  },
  {
    "rank": 169,
    "tier": 23,
    "name": "joshua palmer"
  },
  {
    "rank": 170,
    "tier": 23,
    "name": "quentin johnston"
  },
  {
    "rank": 171,
    "tier": 23,
    "name": "demario douglas"
  },
  {
    "rank": 172,
    "tier": 23,
    "name": "brenton strange"
  },
  {
    "rank": 173,
    "tier": 21,
    "name": "denver broncos"
  },
  {
    "rank": 174,
    "tier": 24,
    "name": "xavier legette"
  },
  {
    "rank": 175,
    "tier": 25,
    "name": "cam ward"
  },
  {
    "rank": 176,
    "tier": 24,
    "name": "blake corum"
  },
  {
    "rank": 177,
    "tier": 23,
    "name": "philadelphia eagles"
  },
  {
    "rank": 178,
    "tier": 25,
    "name": "sam darnold"
  },
  {
    "rank": 179,
    "tier": 25,
    "name": "isaiah likely"
  },
  {
    "rank": 180,
    "tier": 23,
    "name": "pittsburgh steelers"
  },
  {
    "rank": 181,
    "tier": 25,
    "name": "marshawn lloyd"
  },
  {
    "rank": 182,
    "tier": 23,
    "name": "baltimore ravens"
  },
  {
    "rank": 183,
    "tier": 23,
    "name": "minnesota vikings"
  },
  {
    "rank": 184,
    "tier": 25,
    "name": "deandre hopkins"
  },
  {
    "rank": 185,
    "tier": 25,
    "name": "chig okonkwo"
  },
  {
    "rank": 186,
    "tier": 26,
    "name": "pat freiermuth"
  },
  {
    "rank": 187,
    "tier": 25,
    "name": "mike gesicki"
  },
  {
    "rank": 188,
    "tier": 24,
    "name": "houston texans"
  },
  {
    "rank": 189,
    "tier": 26,
    "name": "alec pierce"
  },
  {
    "rank": 190,
    "tier": 26,
    "name": "mason taylor"
  },
  {
    "rank": 191,
    "tier": 25,
    "name": "buffalo bills"
  },
  {
    "rank": 192,
    "tier": 25,
    "name": "detroit lions"
  },
  {
    "rank": 193,
    "tier": 25,
    "name": "kansas city chiefs"
  },
  {
    "rank": 194,
    "tier": 26,
    "name": "cade otton"
  },
  {
    "rank": 195,
    "tier": 25,
    "name": "brandon aubrey"
  },
  {
    "rank": 196,
    "tier": 26,
    "name": "jalen coker"
  },
  {
    "rank": 197,
    "tier": 25,
    "name": "jake bates"
  },
  {
    "rank": 198,
    "tier": 26,
    "name": "justice hill"
  },
  {
    "rank": 199,
    "tier": 26,
    "name": "aaron rodgers"
  },
  {
    "rank": 200,
    "tier": 25,
    "name": "cameron dicker"
  }
]