[
  {
    "rank": 1,
    "tier": 1,
    "name": "bijan robinson"
  },
  {
    "rank": 2,
    "tier": 1,
    "name": "breece hall"
  },
  {
    "rank": 3,
    "tier": 1,
    "name": "saquon barkley"
  },
  {
    "rank": 4,
    "tier": 1,
    "name": "jordan mason"
  },
  {
    "rank": 5,
    "tier": 1,
    "name": "jonathan taylor"
  },
  {
    "rank": 6,
    "tier": 2,
    "name": "devon achane"
  },
  {
    "rank": 7,
    "tier": 2,
    "name": "derrick henry"
  },
  {
    "rank": 8,
    "tier": 2,
    "name": "jahmyr gibbs"
  },
  {
    "rank": 9,
    "tier": 2,
    "name": "josh jacobs"
  },
  {
    "rank": 10,
    "tier": 2,
    "name": "james cook"
  },
  {
    "rank": 11,
    "tier": 3,
    "name": "james conner"
  },
  {
    "rank": 12,
    "tier": 3,
    "name": "alvin kamara"
  },
  {
    "rank": 13,
    "tier": 3,
    "name": "kyren williams"
  },
  {
    "rank": 14,
    "tier": 3,
    "name": "travis etienne"
  },
  {
    "rank": 15,
    "tier": 4,
    "name": "brian robinson"
  },
  {
    "rank": 16,
    "tier": 4,
    "name": "david montgomery"
  },
  {
    "rank": 17,
    "tier": 4,
    "name": "rhamondre stevenson"
  },
  {
    "rank": 18,
    "tier": 4,
    "name": "rachaad white"
  },
  {
    "rank": 19,
    "tier": 5,
    "name": "tony pollard"
  },
  {
    "rank": 20,
    "tier": 5,
    "name": "jk dobbins"
  },
  {
    "rank": 21,
    "tier": 5,
    "name": "zach charbonnet"
  },
  {
    "rank": 22,
    "tier": 5,
    "name": "aaron jones"
  },
  {
    "rank": 23,
    "tier": 5,
    "name": "najee harris"
  },
  {
    "rank": 24,
    "tier": 5,
    "name": "zack moss"
  },
  {
    "rank": 25,
    "tier": 6,
    "name": "jerome ford"
  },
  {
    "rank": 26,
    "tier": 6,
    "name": "zamir white"
  },
  {
    "rank": 27,
    "tier": 6,
    "name": "joe mixon"
  },
  {
    "rank": 28,
    "tier": 6,
    "name": "dandre swift"
  },
  {
    "rank": 29,
    "tier": 6,
    "name": "devin singletary"
  },
  {
    "rank": 30,
    "tier": 7,
    "name": "javonte williams"
  },
  {
    "rank": 31,
    "tier": 7,
    "name": "chuba hubbard"
  },
  {
    "rank": 32,
    "tier": 7,
    "name": "gus edwards"
  },
  {
    "rank": 33,
    "tier": 7,
    "name": "ezekiel elliott"
  },
  {
    "rank": 34,
    "tier": 7,
    "name": "austin ekeler"
  },
  {
    "rank": 35,
    "tier": 8,
    "name": "bucky irving"
  },
  {
    "rank": 36,
    "tier": 8,
    "name": "jaylen warren"
  },
  {
    "rank": 37,
    "tier": 8,
    "name": "alexander mattison"
  },
  {
    "rank": 38,
    "tier": 8,
    "name": "ty chandler"
  },
  {
    "rank": 39,
    "tier": 8,
    "name": "tyjae spears"
  },
  {
    "rank": 40,
    "tier": 8,
    "name": "chase brown"
  }
]