[
  {
    "rank": 1,
    "tier": 1,
    "name": "ceedee lamb"
  },
  {
    "rank": 2,
    "tier": 1,
    "name": "nico collins"
  },
  {
    "rank": 3,
    "tier": 1,
    "name": "justin jefferson"
  },
  {
    "rank": 4,
    "tier": 1,
    "name": "jamarr chase"
  },
  {
    "rank": 5,
    "tier": 2,
    "name": "dk metcalf"
  },
  {
    "rank": 6,
    "tier": 2,
    "name": "marvin harrison"
  },
  {
    "rank": 7,
    "tier": 2,
    "name": "jayden reed"
  },
  {
    "rank": 8,
    "tier": 2,
    "name": "deebo samuel"
  },
  {
    "rank": 9,
    "tier": 2,
    "name": "malik nabers"
  },
  {
    "rank": 10,
    "tier": 2,
    "name": "mike evans"
  },
  {
    "rank": 11,
    "tier": 2,
    "name": "amari cooper"
  },
  {
    "rank": 12,
    "tier": 3,
    "name": "drake london"
  },
  {
    "rank": 13,
    "tier": 3,
    "name": "chris godwin"
  },
  {
    "rank": 14,
    "tier": 3,
    "name": "garrett wilson"
  },
  {
    "rank": 15,
    "tier": 3,
    "name": "brandon aiyuk"
  },
  {
    "rank": 16,
    "tier": 3,
    "name": "chris olave"
  },
  {
    "rank": 17,
    "tier": 4,
    "name": "dj moore"
  },
  {
    "rank": 18,
    "tier": 4,
    "name": "diontae johnson"
  },
  {
    "rank": 19,
    "tier": 4,
    "name": "stefon diggs"
  },
  {
    "rank": 20,
    "tier": 4,
    "name": "george pickens"
  },
  {
    "rank": 21,
    "tier": 5,
    "name": "tyreek hill"
  },
  {
    "rank": 22,
    "tier": 5,
    "name": "zay flowers"
  },
  {
    "rank": 23,
    "tier": 5,
    "name": "tee higgins"
  },
  {
    "rank": 24,
    "tier": 5,
    "name": "xavier worthy"
  },
  {
    "rank": 25,
    "tier": 5,
    "name": "terry mclaurin"
  },
  {
    "rank": 26,
    "tier": 5,
    "name": "brian thomas"
  },
  {
    "rank": 27,
    "tier": 6,
    "name": "rashid shaheed"
  },
  {
    "rank": 28,
    "tier": 6,
    "name": "dontayvion wicks"
  },
  {
    "rank": 29,
    "tier": 6,
    "name": "khalil shakir"
  },
  {
    "rank": 30,
    "tier": 6,
    "name": "christian kirk"
  },
  {
    "rank": 31,
    "tier": 7,
    "name": "jaxon smith-njigba"
  },
  {
    "rank": 32,
    "tier": 7,
    "name": "courtland sutton"
  },
  {
    "rank": 33,
    "tier": 7,
    "name": "michael pittman"
  },
  {
    "rank": 34,
    "tier": 7,
    "name": "darnell mooney"
  },
  {
    "rank": 35,
    "tier": 7,
    "name": "jerry jeudy"
  },
  {
    "rank": 36,
    "tier": 8,
    "name": "rome odunze"
  },
  {
    "rank": 37,
    "tier": 8,
    "name": "romeo doubs"
  },
  {
    "rank": 38,
    "tier": 8,
    "name": "keenan allen"
  },
  {
    "rank": 39,
    "tier": 8,
    "name": "jordan addison"
  },
  {
    "rank": 40,
    "tier": 8,
    "name": "jaylen waddle"
  },
  {
    "rank": 41,
    "tier": 9,
    "name": "xavier legette"
  },
  {
    "rank": 42,
    "tier": 9,
    "name": "jauan jennings"
  },
  {
    "rank": 43,
    "tier": 9,
    "name": "jakobi meyers"
  },
  {
    "rank": 44,
    "tier": 9,
    "name": "wandale robinson"
  },
  {
    "rank": 45,
    "tier": 9,
    "name": "tutu atwell"
  },
  {
    "rank": 46,
    "tier": 10,
    "name": "allen lazard"
  },
  {
    "rank": 47,
    "tier": 10,
    "name": "tyler lockett"
  },
  {
    "rank": 48,
    "tier": 10,
    "name": "josh downs"
  },
  {
    "rank": 49,
    "tier": 10,
    "name": "jordan whittington"
  },
  {
    "rank": 50,
    "tier": 11,
    "name": "demarcus robinson"
  },
  {
    "rank": 51,
    "tier": 11,
    "name": "michael wilson"
  },
  {
    "rank": 52,
    "tier": 11,
    "name": "mike williams"
  },
  {
    "rank": 53,
    "tier": 11,
    "name": "tre tucker"
  },
  {
    "rank": 54,
    "tier": 11,
    "name": "tank dell"
  },
  {
    "rank": 55,
    "tier": 11,
    "name": "keon coleman"
  },
  {
    "rank": 56,
    "tier": 11,
    "name": "gabe davis"
  },
  {
    "rank": 57,
    "tier": 12,
    "name": "jalen tolbert"
  },
  {
    "rank": 58,
    "tier": 12,
    "name": "andrei iosivas"
  },
  {
    "rank": 59,
    "tier": 12,
    "name": "greg dortch"
  },
  {
    "rank": 60,
    "tier": 12,
    "name": "alec pierce"
  }
]