{
  "1264": {
    "player_id": "1264",
    "name": "justin tucker",
    "position": "K",
    "team": "BAL",
    "bye_week": "14",
    "rankingsByScoringType": {
      "std": {
        "rank": 4,
        "tier": 1
      },
      "ppr": null,
      "half": null
    }
  },
  "1348": {
    "player_id": "1348",
    "name": "dustin hopkins",
    "position": "K",
    "team": "CLE",
    "bye_week": "10",
    "rankingsByScoringType": {
      "std": {
        "rank": 18,
        "tier": 5
      },
      "ppr": null,
      "half": null
    }
  },
  "2020": {
    "player_id": "2020",
    "name": "cairo santos",
    "position": "K",
    "team": "CHI",
    "bye_week": "7",
    "rankingsByScoringType": {
      "std": {
        "rank": 11,
        "tier": 3
      },
      "ppr": null,
      "half": null
    }
  },
  "2747": {
    "player_id": "2747",
    "name": "jason myers",
    "position": "K",
    "team": "SEA",
    "bye_week": "10",
    "rankingsByScoringType": {
      "std": {
        "rank": 12,
        "tier": 3
      },
      "ppr": null,
      "half": null
    }
  },
  "3451": {
    "player_id": "3451",
    "name": "kaimi fairbairn",
    "position": "K",
    "team": "HOU",
    "bye_week": "14",
    "rankingsByScoringType": {
      "std": {
        "rank": 3,
        "tier": 1
      },
      "ppr": null,
      "half": null
    }
  },
  "4195": {
    "player_id": "4195",
    "name": "jake elliott",
    "position": "K",
    "team": "PHI",
    "bye_week": "5",
    "rankingsByScoringType": {
      "std": {
        "rank": 5,
        "tier": 2
      },
      "ppr": null,
      "half": null
    }
  },
  "4227": {
    "player_id": "4227",
    "name": "harrison butker",
    "position": "K",
    "team": "KC",
    "bye_week": "6",
    "rankingsByScoringType": {
      "std": {
        "rank": 2,
        "tier": 1
      },
      "ppr": null,
      "half": null
    }
  },
  "4666": {
    "player_id": "4666",
    "name": "younghoe koo",
    "position": "K",
    "team": "ATL",
    "bye_week": "12",
    "rankingsByScoringType": {
      "std": {
        "rank": 8,
        "tier": 3
      },
      "ppr": null,
      "half": null
    }
  },
  "5095": {
    "player_id": "5095",
    "name": "daniel carlson",
    "position": "K",
    "team": "LV",
    "bye_week": "10",
    "rankingsByScoringType": {
      "std": {
        "rank": 19,
        "tier": 5
      },
      "ppr": null,
      "half": null
    }
  },
  "5119": {
    "player_id": "5119",
    "name": "jason sanders",
    "position": "K",
    "team": "MIA",
    "bye_week": "6",
    "rankingsByScoringType": {
      "std": {
        "rank": 7,
        "tier": 2
      },
      "ppr": null,
      "half": null
    }
  },
  "6083": {
    "player_id": "6083",
    "name": "matt gay",
    "position": "K",
    "team": "IND",
    "bye_week": "14",
    "rankingsByScoringType": {
      "std": {
        "rank": 16,
        "tier": 4
      },
      "ppr": null,
      "half": null
    }
  },
  "6650": {
    "player_id": "6650",
    "name": "chase mclaughlin",
    "position": "K",
    "team": "TB",
    "bye_week": "11",
    "rankingsByScoringType": {
      "std": {
        "rank": 17,
        "tier": 4
      },
      "ppr": null,
      "half": null
    }
  },
  "7042": {
    "player_id": "7042",
    "name": "tyler bass",
    "position": "K",
    "team": "BUF",
    "bye_week": "12",
    "rankingsByScoringType": {
      "std": {
        "rank": 6,
        "tier": 2
      },
      "ppr": null,
      "half": null
    }
  },
  "7839": {
    "player_id": "7839",
    "name": "evan mcpherson",
    "position": "K",
    "team": "CIN",
    "bye_week": "12",
    "rankingsByScoringType": {
      "std": {
        "rank": 1,
        "tier": 1
      },
      "ppr": null,
      "half": null
    }
  },
  "8259": {
    "player_id": "8259",
    "name": "cameron dicker",
    "position": "K",
    "team": "LAC",
    "bye_week": "5",
    "rankingsByScoringType": {
      "std": {
        "rank": 13,
        "tier": 4
      },
      "ppr": null,
      "half": null
    }
  },
  "10937": {
    "player_id": "10937",
    "name": "jake moody",
    "position": "K",
    "team": "SF",
    "bye_week": "9",
    "rankingsByScoringType": {
      "std": {
        "rank": 10,
        "tier": 3
      },
      "ppr": null,
      "half": null
    }
  },
  "11058": {
    "player_id": "11058",
    "name": "blake grupe",
    "position": "K",
    "team": "NO",
    "bye_week": "12",
    "rankingsByScoringType": {
      "std": {
        "rank": 15,
        "tier": 4
      },
      "ppr": null,
      "half": null
    }
  },
  "11533": {
    "player_id": "11533",
    "name": "brandon aubrey",
    "position": "K",
    "team": "DAL",
    "bye_week": "7",
    "rankingsByScoringType": {
      "std": {
        "rank": 9,
        "tier": 3
      },
      "ppr": null,
      "half": null
    }
  },
  "11539": {
    "player_id": "11539",
    "name": "jake bates",
    "position": "K",
    "team": "DET",
    "bye_week": "5",
    "rankingsByScoringType": {
      "std": {
        "rank": 14,
        "tier": 4
      },
      "ppr": null,
      "half": null
    }
  },
  "11789": {
    "player_id": "11789",
    "name": "joshua karty",
    "position": "K",
    "team": "LAR",
    "bye_week": "6",
    "rankingsByScoringType": {
      "std": {
        "rank": 20,
        "tier": 5
      },
      "ppr": null,
      "half": null
    }
  }
}